{"cameraMode":{"drawMode":0,"name":"Shaded","section":"Shading Mode"},"sceneLighting":true,"audioPlay":false,"sceneViewState":{"m_AlwaysRefresh":false,"showFog":true,"showSkybox":true,"showFlares":true,"showImageEffects":true,"showParticleSystems":true,"showVisualEffectGraphs":true,"m_FxEnabled":true},"in2DMode":false,"pivot":{"x":-0.9253168106079102,"y":-2.1481449604034426,"z":-4.256207466125488},"rotation":{"x":-0.013152869418263436,"y":0.7282687425613403,"z":-0.685025155544281,"w":-0.01398438960313797},"size":10.306352615356446,"orthographic":false}